CHANGES.rst
CONTRIBUTORS.rst
HOWTO_DEVELOP.rst
LICENSE.rst
MANIFEST.in
README.rst
setup.cfg
setup.py
docs/LICENSE.GPL
docs/LICENSE.rst
docs/index.rst
src/collective/__init__.py
src/collective.multitheme.egg-info/PKG-INFO
src/collective.multitheme.egg-info/SOURCES.txt
src/collective.multitheme.egg-info/dependency_links.txt
src/collective.multitheme.egg-info/entry_points.txt
src/collective.multitheme.egg-info/namespace_packages.txt
src/collective.multitheme.egg-info/not-zip-safe
src/collective.multitheme.egg-info/requires.txt
src/collective.multitheme.egg-info/top_level.txt
src/collective/multitheme/__init__.py
src/collective/multitheme/configure.zcml
src/collective/multitheme/interfaces.py
src/collective/multitheme/setuphandlers.py
src/collective/multitheme/testing.py
src/collective/multitheme/vocabulary.py
src/collective/multitheme/browser/__init__.py
src/collective/multitheme/browser/configure.zcml
src/collective/multitheme/browser/dropdown.py
src/collective/multitheme/browser/dropdown_recurse.pt
src/collective/multitheme/browser/dropdown_sections.pt
src/collective/multitheme/browser/left_sitemap.pt
src/collective/multitheme/browser/left_sitemap.py
src/collective/multitheme/browser/menu_sitemap.pt
src/collective/multitheme/browser/menu_sitemap.py
src/collective/multitheme/browser/mobile_sitemap.pt
src/collective/multitheme/browser/sitemap-item.pt
src/collective/multitheme/browser/visual-sitemap-item.pt
src/collective/multitheme/browser/visual_sitemap.pt
src/collective/multitheme/browser/visual_sitemap.py
src/collective/multitheme/browser/overrides/.gitkeep
src/collective/multitheme/browser/static/.gitkeep
src/collective/multitheme/locales/collective.multitheme.pot
src/collective/multitheme/locales/update.sh
src/collective/multitheme/profiles/default/browserlayer.xml
src/collective/multitheme/profiles/default/metadata.xml
src/collective/multitheme/profiles/default/registry.xml
src/collective/multitheme/profiles/default/theme.xml
src/collective/multitheme/profiles/democontent/metadata.xml
src/collective/multitheme/profiles/democontent/multitheme_content.txt
src/collective/multitheme/profiles/uninstall/browserlayer.xml
src/collective/multitheme/profiles/uninstall/theme.xml
src/collective/multitheme/tests/__init__.py
src/collective/multitheme/tests/test_robot.py
src/collective/multitheme/tests/test_setup.py
