Metadata-Version: 1.1
Name: collective.multitheme
Version: 1.0
Summary: A (Multi) Theme for Plone 5
Home-page: https://pypi.python.org/pypi/collective.multitheme
Author: Espen Moe-Nilssen
Author-email: espen@medialog.no
License: GPL version 2
Keywords: Python Plone
Platform: UNKNOWN
Classifier: Environment :: Web Environment
Classifier: Framework :: Plone
Classifier: Framework :: Plone :: Theme
Classifier: Framework :: Plone :: 5.0
Classifier: Framework :: Plone :: 5.1
Classifier: Programming Language :: Python
Classifier: Programming Language :: Python :: 2.7
Classifier: Operating System :: OS Independent
Classifier: License :: OSI Approved :: GNU General Public License v2 (GPLv2)
